spacyThrift/SpacyThrift.py
spacyThrift/__init__.py
spacyThrift/constants.py
spacyThrift/service.py
spacyThrift/ttypes.py
spacy_thrift-0.5.0.dist-info/METADATA
spacy_thrift-0.5.0.dist-info/RECORD
spacy_thrift-0.5.0.dist-info/WHEEL
spacy_thrift-0.5.0.dist-info/top_level.txt
