Metadata-Version: 2.1
Name: spacy-thrift
Version: 0.5.0
Summary: spaCy-as-a-service using Thrift
Home-page: https://github.com/turbolent/spacy-thrift
Author: Bastian Mueller
Author-email: bastian@turbolent.com
License: UNKNOWN
Keywords: natural language processing,nlp
Platform: UNKNOWN
Classifier: License :: OSI Approved :: MIT License
Classifier: Topic :: Text Processing
Requires-Dist: click (==6.7)
Requires-Dist: thrift (==0.11.0)
Requires-Dist: spacy (==2.0.12)
Requires-Dist: coloredlogs (==10.0)
